{
  "formatVersion": 1,
  "database": {
    "version": 1,
    "identityHash": "97dc9c47f320c524a224b0e4ec908cb7",
    "entities": [
      {
        "tableName": "note_table",
        "createSql": "CREATE TABLE IF NOT EXISTS `${TABLE_NAME}` (`NoteId` INTEGER PRIMARY KEY AUTOINCREMENT, `Title` TEXT NOT NULL, `Description` TEXT NOT NULL, `EditTime` INTEGER NOT NULL, `Pin` INTEGER NOT NULL, `Archive` INTEGER NOT NULL, `BackgroundColor` INTEGER NOT NULL, `BackgroundImage` INTEGER NOT NULL)",
        "fields": [
          {
            "fieldPath": "noteId",
            "columnName": "NoteId",
            "affinity": "INTEGER",
            "notNull": false
          },
          {
            "fieldPath": "title",
            "columnName": "Title",
            "affinity": "TEXT",
            "notNull": true
          },
          {
            "fieldPath": "description",
            "columnName": "Description",
            "affinity": "TEXT",
            "notNull": true
          },
          {
            "fieldPath": "editTime",
            "columnName": "EditTime",
            "affinity": "INTEGER",
            "notNull": true
          },
          {
            "fieldPath": "pin",
            "columnName": "Pin",
            "affinity": "INTEGER",
            "notNull": true
          },
          {
            "fieldPath": "archive",
            "columnName": "Archive",
            "affinity": "INTEGER",
            "notNull": true
          },
          {
            "fieldPath": "backgroundColor",
            "columnName": "BackgroundColor",
            "affinity": "INTEGER",
            "notNull": true
          },
          {
            "fieldPath": "backgroundImage",
            "columnName": "BackgroundImage",
            "affinity": "INTEGER",
            "notNull": true
          }
        ],
        "primaryKey": {
          "autoGenerate": true,
          "columnNames": [
            "NoteId"
          ]
        },
        "indices": [],
        "foreignKeys": []
      },
      {
        "tableName": "label_table",
        "createSql": "CREATE TABLE IF NOT EXISTS `${TABLE_NAME}` (`LabelId` INTEGER PRIMARY KEY AUTOINCREMENT, `LabelName` TEXT NOT NULL)",
        "fields": [
          {
            "fieldPath": "labelId",
            "columnName": "LabelId",
            "affinity": "INTEGER",
            "notNull": false
          },
          {
            "fieldPath": "labelName",
            "columnName": "LabelName",
            "affinity": "TEXT",
            "notNull": true
          }
        ],
        "primaryKey": {
          "autoGenerate": true,
          "columnNames": [
            "LabelId"
          ]
        },
        "indices": [],
        "foreignKeys": []
      }
    ],
    "views": [],
    "setupQueries": [
      "CREATE TABLE IF NOT EXISTS room_master_table (id INTEGER PRIMARY KEY,identity_hash TEXT)",
      "INSERT OR REPLACE INTO room_master_table (id,identity_hash) VALUES(42, '97dc9c47f320c524a224b0e4ec908cb7')"
    ]
  }
}